README.md
setup.cfg
setup.py
pegasi/README.md
pegasi/__init__.py
pegasi/pic.hy
pegasi/req.py
pegasi.egg-info/PKG-INFO
pegasi.egg-info/SOURCES.txt
pegasi.egg-info/dependency_links.txt
pegasi.egg-info/requires.txt
pegasi.egg-info/top_level.txt