Metadata-Version: 2.1
Name: pegasi
Version: 0.40006
Summary: Run on my cloud
Home-page: https://github.com/user/reponame
Author: ShinSheel
Author-email: wladgavrilov@gmail.com
License: MIT
Download-URL: https://github.com/user/reponame/archive/v_01.tar.gz
Keywords: SOME,MEANINGFULL,KEYWORDS
Platform: UNKNOWN
Classifier: Development Status :: 3 - Alpha
Classifier: Intended Audience :: Developers
Classifier: Topic :: Software Development :: Build Tools
Classifier: License :: OSI Approved :: MIT License
Classifier: Programming Language :: Python :: 3
Classifier: Programming Language :: Python :: 3.4
Classifier: Programming Language :: Python :: 3.5
Classifier: Programming Language :: Python :: 3.6
